CroemincSDK/CroemincGateway.py
CroemincSDK/CroemincSDK.py
CroemincSDK/__init__.py
CroemincSDK/AESHelper/AESHandler.py
CroemincSDK/AESHelper/__init__.py
CroemincSDK/Entities/ACH.py
CroemincSDK/Entities/Address.py
CroemincSDK/Entities/BaseEntity.py
CroemincSDK/Entities/Beneficiary.py
CroemincSDK/Entities/CreditCard.py
CroemincSDK/Entities/CreditCardResponse.py
CroemincSDK/Entities/Customer.py
CroemincSDK/Entities/CustomerEntities.py
CroemincSDK/Entities/CustomerEntityResponse.py
CroemincSDK/Entities/CustomerOptions.py
CroemincSDK/Entities/CustomerResponse.py
CroemincSDK/Entities/CustomerSearch.py
CroemincSDK/Entities/CustomerSearchOption.py
CroemincSDK/Entities/Instrument.py
CroemincSDK/Entities/InstrumentResponse.py
CroemincSDK/Entities/ParameterFilter.py
CroemincSDK/Entities/PaymentInstruction.py
CroemincSDK/Entities/PaymentInstructionResponse.py
CroemincSDK/Entities/RequestModel.py
CroemincSDK/Entities/ResponseModel.py
CroemincSDK/Entities/SearchFilter.py
CroemincSDK/Entities/Service.py
CroemincSDK/Entities/Test.py
CroemincSDK/Entities/Transaction.py
CroemincSDK/Entities/TransactionOptions.py
CroemincSDK/Entities/TransactionResponse.py
CroemincSDK/Entities/TransactionSearchRequest.py
CroemincSDK/Entities/ValidationError.py
CroemincSDK/Entities/Wallet.py
CroemincSDK/Entities/__init__.py
CroemincSDK/Helper/TranslationHelper.py
CroemincSDK/Helper/__init__.py
CroemincSDK/Manager/CustomerManager.py
CroemincSDK/Manager/TransactionManager.py
CroemincSDK/Manager/__init__.py
CroemincSDK-0.1.2.dist-info/METADATA
CroemincSDK-0.1.2.dist-info/WHEEL
CroemincSDK-0.1.2.dist-info/top_level.txt
CroemincSDK-0.1.2.dist-info/RECORD
