Metadata-Version: 2.1
Name: CroemincSDK
Version: 0.1.2
Summary: This SDK provides an organized way to connect and consume Croeminc payment gateway, card storage, and customer management service
Home-page: https://dev.azure.com/croeminc/NeoGateway/_git/NeoGateway.SDK.Python.Package
Author: Muhammad Umer farooq
Author-email: support@croeminc.com
Classifier: Programming Language :: Python :: 3
Classifier: License :: OSI Approved :: MIT License
Classifier: Operating System :: OS Independent
Requires-Python: >=3.6
Requires-Dist: jsonpickle >=3.2.1
Requires-Dist: requests >=2.32.3
